ZetcodeJiaochengZhengli/README.md
ZetcodeJiaochengZhengli/__init__.py
ZetcodeJiaochengZhengli/__main__.py
ZetcodeJiaochengZhengli/file.epub
ZetcodeJiaochengZhengli/index.html
ZetcodeJiaochengZhengli/css/__init__.py
ZetcodeJiaochengZhengli/css/annotations.css
ZetcodeJiaochengZhengli/css/main.css
ZetcodeJiaochengZhengli/css/normalize.css
ZetcodeJiaochengZhengli/css/popup.css
ZetcodeJiaochengZhengli/font/__init__.py
ZetcodeJiaochengZhengli/font/fontello.eot
ZetcodeJiaochengZhengli/font/fontello.svg
ZetcodeJiaochengZhengli/font/fontello.ttf
ZetcodeJiaochengZhengli/font/fontello.woff
ZetcodeJiaochengZhengli/img/__init__.py
ZetcodeJiaochengZhengli/img/annotator-glyph-sprite.png
ZetcodeJiaochengZhengli/img/annotator-icon-sprite.png
ZetcodeJiaochengZhengli/img/apple-touch-icon.png
ZetcodeJiaochengZhengli/img/cancelfullscreen.png
ZetcodeJiaochengZhengli/img/close.png
ZetcodeJiaochengZhengli/img/fullscreen.png
ZetcodeJiaochengZhengli/img/loader.gif
ZetcodeJiaochengZhengli/img/menu-icon.png
ZetcodeJiaochengZhengli/img/save.png
ZetcodeJiaochengZhengli/img/saved.png
ZetcodeJiaochengZhengli/img/settings-s.png
ZetcodeJiaochengZhengli/img/settings.png
ZetcodeJiaochengZhengli/img/star.png
ZetcodeJiaochengZhengli/js/__init__.py
ZetcodeJiaochengZhengli/js/epub.js
ZetcodeJiaochengZhengli/js/epub.min.js
ZetcodeJiaochengZhengli/js/epub.min.map
ZetcodeJiaochengZhengli/js/hooks.min.js
ZetcodeJiaochengZhengli/js/hooks.min.map
ZetcodeJiaochengZhengli/js/reader.js
ZetcodeJiaochengZhengli/js/reader.js.map
ZetcodeJiaochengZhengli/js/reader.min.js
ZetcodeJiaochengZhengli/js/reader.min.map
ZetcodeJiaochengZhengli/js/hooks/__init__.py
ZetcodeJiaochengZhengli/js/hooks/extensions/__init__.py
ZetcodeJiaochengZhengli/js/hooks/extensions/highlight.js
ZetcodeJiaochengZhengli/js/libs/__init__.py
ZetcodeJiaochengZhengli/js/libs/jquery.min.js
ZetcodeJiaochengZhengli/js/libs/localforage.min.js
ZetcodeJiaochengZhengli/js/libs/screenfull.js
ZetcodeJiaochengZhengli/js/libs/screenfull.min.js
zetcode_jiaocheng_zhengli-2024.3.2.0.dist-info/METADATA
zetcode_jiaocheng_zhengli-2024.3.2.0.dist-info/WHEEL
zetcode_jiaocheng_zhengli-2024.3.2.0.dist-info/entry_points.txt
zetcode_jiaocheng_zhengli-2024.3.2.0.dist-info/top_level.txt
zetcode_jiaocheng_zhengli-2024.3.2.0.dist-info/RECORD
